README.rst
setup.py
typedtuple/__init__.py
typedtuple.egg-info/PKG-INFO
typedtuple.egg-info/SOURCES.txt
typedtuple.egg-info/dependency_links.txt
typedtuple.egg-info/requires.txt
typedtuple.egg-info/top_level.txt